Workbook

Sheet Leia-me
A1: MODELO DE GESTÃO DE ACADEMIA – V2 EXECUTIVO
A2: Objetivo: apoiar gestão operacional, financeira, comercial e apresentação executiva.
A3: Substitua os exemplos pelos dados reais. As abas de premissas alimentam os indicadores e projeções.
A4: Fluxo recomendado: Premissas → Operação/Alunos → Receitas/Despesas → Indicadores → Dashboard.
A5: Importante: CAC e LTV são indicadores gerenciais estimados; ajuste as premissas conforme seus dados reais.

Sheet Premissas
A1: PARÂMETRO | B1: VALOR | C1: UNIDADE | D1: OBSERVAÇÃO
A2: Mensalidade média musculação | B2: 150 | C2: R$/mês | D2: Exemplo editável
A3: Mensalidade média lutas | B3: 190 | C3: R$/mês | D3: Exemplo editável
A4: Mensalidade média balé | B4: 140 | C4: R$/mês | D4: Exemplo editável
A5: Taxa média de recebimento | B5: 0.97 | C5: % | D5: Receita efetivamente recebida
A6: Churn mensal estimado | B6: 0.05 | C6: % | D6: Cancelamentos / base inicial
A7: CAC estimado | B7: 100 | C7: R$/aluno | D7: Custo comercial por novo aluno
A8: Margem de contribuição média | B8: 0.65 | C8: % | D8: Após custos variáveis
A9: Crescimento mensal projetado | B9: 0.03 | C9: % | D9: Para projeção de faturamento
A10: Custos fixos mensais | B10: 18000 | C10: R$/mês | D10: Base inicial
A11: Meta de alunos ativos | B11: 300 | C11: alunos | D11: Meta gerencial
A12: Dias de funcionamento/mês | B12: 26 | C12: dias | D12: Premissa operacional

Sheet Alunos
A1: ID | B1: Nome | C1: Modalidade | D1: Plano | E1: Data Matrícula | F1: Mensalidade | G1: Status | H1: Data Cancelamento | I1: Origem | J1: Observação
A2: 1 | B2: Aluno 001 | C2: Musculação | D2: Mensal | E2: 01/09/2026 | F2: 150 | G2: Ativo | I2: Instagram
A3: 2 | B3: Aluno 002 | C3: Jiu-jítsu | D3: Combate | E3: 03/09/2026 | F3: 190 | G3: Ativo | I3: Google
A4: 3 | B4: Aluno 003 | C4: Muay Thai | D4: Multitreino | E4: 05/09/2026 | F4: 220 | G4: Ativo | I4: Indicação
A5: 4 | B5: Aluno 004 | C5: Balé | D5: Mensal | E5: 06/09/2026 | F5: 140 | G5: Ativo | I5: Instagram
A6: 5 | B6: Aluno 005 | C6: Capoeira | D6: Mensal | E6: 10/09/2026 | F6: 130 | G6: Cancelado | H6: 15/09/2026 | I6: Instagram
A7: 6 | B7: Aluno 006 | C7: Musculação | D7: Mensal | E7: 12/09/2026 | F7: 150 | G7: Ativo | I7: Indicação

Sheet Turmas
A1: Código | B1: Modalidade | C1: Dia | D1: Horário | E1: Professor | F1: Capacidade | G1: Matriculados | H1: Presença Média | I1: Ocupação % | J1: Custo Mensal | K1: Receita Potencial | L1: Margem Estimada
A2: MUS06 | B2: Musculação | C2: Seg-Sáb | D2: 06-08h | E2: Equipe | F2: 8 | G2: 7 | H2: 6.2 | I2: =IFERROR(G2/F2,0) -> 0.875 | J2: 4500 | K2: =G2*IF(B2="Musculação",Premissas!$B$2,IF(B2="Balé",Premissas!$B$4,Premissas!$B$3)) -> 1050 | L2: =IFERROR((K2-J2)/K2,0) -> -3.2857143
A3: MUS08 | B3: Musculação | C3: Seg-Sáb | D3: 08-10h | E3: Equipe | F3: 8 | G3: 6 | H3: 5 | I3: =IFERROR(G3/F3,0) -> 0.75 | J3: 4500 | K3: =G3*IF(B3="Musculação",Premissas!$B$2,IF(B3="Balé",Premissas!$B$4,Premissas!$B$3)) -> 900 | L3: =IFERROR((K3-J3)/K3,0) -> -4
A4: MUS18 | B4: Musculação | C4: Seg-Sáb | D4: 18-20h | E4: Equipe | F4: 8 | G4: 8 | H4: 7.2 | I4: =IFERROR(G4/F4,0) -> 1 | J4: 4500 | K4: =G4*IF(B4="Musculação",Premissas!$B$2,IF(B4="Balé",Premissas!$B$4,Premissas!$B$3)) -> 1200 | L4: =IFERROR((K4-J4)/K4,0) -> -2.75
A5: JJ19 | B5: Jiu-jítsu | C5: Seg | D5: 19h | E5: Prof. A | F5: 20 | G5: 17 | H5: 14 | I5: =IFERROR(G5/F5,0) -> 0.85 | J5: 480 | K5: =G5*IF(B5="Musculação",Premissas!$B$2,IF(B5="Balé",Premissas!$B$4,Premissas!$B$3)) -> 3230 | L5: =IFERROR((K5-J5)/K5,0) -> 0.85139319
A6: JJ20 | B6: Jiu-jítsu | C6: Qua | D6: 19h | E6: Prof. A | F6: 20 | G6: 12 | H6: 10 | I6: =IFERROR(G6/F6,0) -> 0.6 | J6: 480 | K6: =G6*IF(B6="Musculação",Premissas!$B$2,IF(B6="Balé",Premissas!$B$4,Premissas!$B$3)) -> 2280 | L6: =IFERROR((K6-J6)/K6,0) -> 0.78947368
A7: JJ21 | B7: Jiu-jítsu | C7: Sex | D7: 19h | E7: Prof. A | F7: 20 | G7: 10 | H7: 8 | I7: =IFERROR(G7/F7,0) -> 0.5 | J7: 480 | K7: =G7*IF(B7="Musculação",Premissas!$B$2,IF(B7="Balé",Premissas!$B$4,Premissas!$B$3)) -> 1900 | L7: =IFERROR((K7-J7)/K7,0) -> 0.74736842
A8: MT20 | B8: Muay Thai | C8: Ter | D8: 20h | E8: Prof. B | F8: 20 | G8: 18 | H8: 15 | I8: =IFERROR(G8/F8,0) -> 0.9 | J8: 480 | K8: =G8*IF(B8="Musculação",Premissas!$B$2,IF(B8="Balé",Premissas!$B$4,Premissas!$B$3)) -> 3420 | L8: =IFERROR((K8-J8)/K8,0) -> 0.85964912
A9: MT20Q | B9: Muay Thai | C9: Qui | D9: 20h | E9: Prof. B | F9: 20 | G9: 15 | H9: 12 | I9: =IFERROR(G9/F9,0) -> 0.75 | J9: 480 | K9: =G9*IF(B9="Musculação",Premissas!$B$2,IF(B9="Balé",Premissas!$B$4,Premissas!$B$3)) -> 2850 | L9: =IFERROR((K9-J9)/K9,0) -> 0.83157895
A10: CP18 | B10: Capoeira | C10: Qua | D10: 18h | E10: Prof. C | F10: 20 | G10: 8 | H10: 6 | I10: =IFERROR(G10/F10,0) -> 0.4 | J10: 400 | K10: =G10*IF(B10="Musculação",Premissas!$B$2,IF(B10="Balé",Premissas!$B$4,Premissas!$B$3)) -> 1520 | L10: =IFERROR((K10-J10)/K10,0) -> 0.73684211
A11: KAR19 | B11: Karatê | C11: Qui | D11: 19h | E11: Prof. D | F11: 20 | G11: 10 | H11: 8 | I11: =IFERROR(G11/F11,0) -> 0.5 | J11: 240 | K11: =G11*IF(B11="Musculação",Premissas!$B$2,IF(B11="Balé",Premissas!$B$4,Premissas!$B$3)) -> 1900 | L11: =IFERROR((K11-J11)/K11,0) -> 0.87368421
A12: BAL10 | B12: Balé | C12: Sáb | D12: 10h | E12: Prof. E | F12: 15 | G12: 11 | H12: 9 | I12: =IFERROR(G12/F12,0) -> 0.73333333 | J12: 240 | K12: =G12*IF(B12="Musculação",Premissas!$B$2,IF(B12="Balé",Premissas!$B$4,Premissas!$B$3)) -> 1540 | L12: =IFERROR((K12-J12)/K12,0) -> 0.84415584

Sheet Receitas
A1: Data | B1: ID Aluno | C1: Cliente | D1: Modalidade | E1: Tipo | F1: Valor Previsto | G1: Valor Recebido | H1: Forma Pagamento | I1: Status | J1: Mês
A2: 05/09/2026 | B2: 1 | C2: Aluno 001 | D2: Musculação | E2: Mensalidade | F2: 150 | G2: 150 | H2: PIX | I2: Pago | J2: 09/2026
A3: 05/09/2026 | B3: 2 | C3: Aluno 002 | D3: Jiu-jítsu | E3: Mensalidade | F3: 190 | G3: 190 | H3: Cartão | I3: Pago | J3: 09/2026
A4: 06/09/2026 | B4: 3 | C4: Aluno 003 | D4: Muay Thai | E4: Mensalidade | F4: 220 | G4: 220 | H4: PIX | I4: Pago | J4: 09/2026
A5: 07/09/2026 | B5: 4 | C5: Aluno 004 | D5: Balé | E5: Mensalidade | F5: 140 | G5: 0 | H5: Boleto | I5: Pendente | J5: 09/2026
A6: 10/09/2026 | D6: Diversas | E6: Produtos | F6: 500 | G6: 500 | H6: PIX | I6: Pago | J6: 09/2026

Sheet Despesas
A1: Data | B1: Categoria | C1: Descrição | D1: Fixa/Variável | E1: Centro Custo | F1: Valor | G1: Pago? | H1: Mês
A2: 01/09/2026 | B2: Pessoal | C2: Professores | D2: Variável | E2: Operação | F2: 6500 | G2: Sim | H2: 09/2026
A3: 01/09/2026 | B3: Aluguel | C3: Espaço | D3: Fixa | E3: Administrativo | F3: 6000 | G3: Sim | H3: 09/2026
A4: 03/09/2026 | B4: Energia | C4: Energia elétrica | D4: Fixa | E4: Estrutura | F4: 1800 | G4: Sim | H4: 09/2026
A5: 05/09/2026 | B5: Marketing | C5: Anúncios | D5: Variável | E5: Comercial | F5: 1000 | G5: Sim | H5: 09/2026
A6: 07/09/2026 | B6: Manutenção | C6: Equipamentos | D6: Variável | E6: Estrutura | F6: 700 | G6: Não | H6: 09/2026
A7: 08/09/2026 | B7: Sistema | C7: Software gestão | D7: Fixa | E7: Administrativo | F7: 300 | G7: Sim | H7: 09/2026
A8: 10/09/2026 | B8: Limpeza | C8: Materiais | D8: Fixa | E8: Estrutura | F8: 600 | G8: Sim | H8: 09/2026

Sheet Leads
A1: Data | B1: Nome | C1: Origem | D1: Interesse | E1: Experimental | F1: Compareceu | G1: Matriculou | H1: Valor Plano | I1: CAC | J1: Status
A2: 01/09/2026 | B2: Lead 001 | C2: Instagram | D2: Musculação | E2: Sim | F2: Sim | G2: Sim | H2: 150 | I2: 100 | J2: Matriculado
A3: 02/09/2026 | B3: Lead 002 | C3: Google | D3: Jiu-jítsu | E3: Sim | F3: Sim | G3: Não | H3: 190 | I3: 100 | J3: Não convertido
A4: 03/09/2026 | B4: Lead 003 | C4: Indicação | D4: Muay Thai | E4: Sim | F4: Sim | G4: Sim | H4: 220 | I4: 100 | J4: Matriculado
A5: 04/09/2026 | B5: Lead 004 | C5: Instagram | D5: Balé | E5: Sim | F5: Não | G5: Não | H5: 140 | I5: 100 | J5: Sem comparecimento
A6: 05/09/2026 | B6: Lead 005 | C6: Facebook | D6: Musculação | E6: Sim | F6: Sim | G6: Sim | H6: 150 | I6: 100 | J6: Matriculado

Sheet DRE_12M
A1: DRE GERENCIAL | B1: Mês 1 | C1: Mês 2 | D1: Mês 3 | E1: Mês 4 | F1: Mês 5 | G1: Mês 6 | H1: Mês 7 | I1: Mês 8 | J1: Mês 9 | K1: Mês 10 | L1: Mês 11 | M1: Mês 12
A2: Receita Bruta | B2: =SUM(Receitas!F:F) -> 1200 | C2: =B2*(1+Premissas!$B$9) -> 1236 | D2: =C2*(1+Premissas!$B$9) -> 1273.08 | E2: =D2*(1+Premissas!$B$9) -> 1311.2724 | F2: =E2*(1+Premissas!$B$9) -> 1350.6106 | G2: =F2*(1+Premissas!$B$9) -> 1391.1289 | H2: =G2*(1+Premissas!$B$9) -> 1432.8628 | I2: =H2*(1+Premissas!$B$9) -> 1475.8486 | J2: =I2*(1+Premissas!$B$9) -> 1520.1241 | ... M2: =L2*(1+Premissas!$B$9) -> 1661.0806
A3: (-) Inadimplência/Descontos | B3: =B2*(1-Premissas!$B$5) -> 36 | C3: =C2*(1-Premissas!$B$5) -> 37.08 | D3: =D2*(1-Premissas!$B$5) -> 38.1924 | E3: =E2*(1-Premissas!$B$5) -> 39.338172 | F3: =F2*(1-Premissas!$B$5) -> 40.518317 | G3: =G2*(1-Premissas!$B$5) -> 41.733867 | H3: =H2*(1-Premissas!$B$5) -> 42.985883 | I3: =I2*(1-Premissas!$B$5) -> 44.275459 | ... M3: =M2*(1-Premissas!$B$5) -> 49.832419
A4: Receita Líquida | B4: =B2-B3 -> 1164 | C4: =C2-C3 -> 1198.92 | D4: =D2-D3 -> 1234.8876 | E4: =E2-E3 -> 1271.9342 | F4: =F2-F3 -> 1310.0923 | G4: =G2-G3 -> 1349.395 | H4: =H2-H3 -> 1389.8769 | I4: =I2-I3 -> 1431.5732 | ... M4: =M2-M3 -> 1611.2482
A5: (-) Custos Variáveis | B5: =B4*(1-Premissas!$B$8) -> 407.4 | C5: =C4*(1-Premissas!$B$8) -> 419.622 | D5: =D4*(1-Premissas!$B$8) -> 432.21066 | E5: =E4*(1-Premissas!$B$8) -> 445.17698 | F5: =F4*(1-Premissas!$B$8) -> 458.53229 | G5: =G4*(1-Premissas!$B$8) -> 472.28826 | H5: =H4*(1-Premissas!$B$8) -> 486.45691 | I5: =I4*(1-Premissas!$B$8) -> 501.05061 | ... M5: =M4*(1-Premissas!$B$8) -> 563.93688
A6: Margem de Contribuição | B6: =B4-B5 -> 756.6 | C6: =C4-C5 -> 779.298 | D6: =D4-D5 -> 802.67694 | E6: =E4-E5 -> 826.75725 | F6: =F4-F5 -> 851.55997 | G6: =G4-G5 -> 877.10676 | H6: =H4-H5 -> 903.41997 | I6: =I4-I5 -> 930.52257 | ... M6: =M4-M5 -> 1047.3113
A7: (-) Custos Fixos | B7: =Premissas!$B$10 -> 18000 | C7: =Premissas!$B$10 -> 18000 | D7: =Premissas!$B$10 -> 18000 | E7: =Premissas!$B$10 -> 18000 | F7: =Premissas!$B$10 -> 18000 | G7: =Premissas!$B$10 -> 18000 | H7: =Premissas!$B$10 -> 18000 | I7: =Premissas!$B$10 -> 18000 | ... M7: =Premissas!$B$10 -> 18000
A8: Resultado Operacional | B8: =B6-B7 -> -17243.4 | C8: =C6-C7 -> -17220.702 | D8: =D6-D7 -> -17197.323 | E8: =E6-E7 -> -17173.243 | F8: =F6-F7 -> -17148.44 | G8: =G6-G7 -> -17122.893 | H8: =H6-H7 -> -17096.58 | I8: =I6-I7 -> -17069.477 | ... M8: =M6-M7 -> -16952.689
A9: Margem Operacional | B9: =IFERROR(B8/B4,0) -> -14.813918 | C9: =IFERROR(C8/C4,0) -> -14.363512 | D9: =IFERROR(D8/D4,0) -> -13.926225 | E9: =IFERROR(E8/E4,0) -> -13.501675 | F9: =IFERROR(F8/F4,0) -> -13.08949 | G9: =IFERROR(G8/G4,0) -> -12.689311 | H9: =IFERROR(H8/H4,0) -> -12.300787 | I9: =IFERROR(I8/I4,0) -> -11.92358 | ... M9: =IFERROR(M8/M4,0) -> -10.521463

Sheet Fluxo_Caixa_12M
A1: FLUXO DE CAIXA | B1: Mês 1 | C1: Mês 2 | D1: Mês 3 | E1: Mês 4 | F1: Mês 5 | G1: Mês 6 | H1: Mês 7 | I1: Mês 8 | J1: Mês 9 | K1: Mês 10 | L1: Mês 11 | M1: Mês 12
A2: Saldo Inicial | B2: =0 -> 0 | C2: =B6 -> -17243.4 | D2: =C6 -> -34464.102 | E2: =D6 -> -51661.425 | F2: =E6 -> -68834.668 | G2: =F6 -> -85983.108 | H2: =G6 -> -103106 | I2: =H6 -> -120202.58 | J2: =I6 -> -137272.06 | ... M2: =L6 -> -188309.62
A3: Entradas | B3: =DRE_12M!B4 -> 1164 | C3: =DRE_12M!C4 -> 1198.92 | D3: =DRE_12M!D4 -> 1234.8876 | E3: =DRE_12M!E4 -> 1271.9342 | F3: =DRE_12M!F4 -> 1310.0923 | G3: =DRE_12M!G4 -> 1349.395 | H3: =DRE_12M!H4 -> 1389.8769 | I3: =DRE_12M!I4 -> 1431.5732 | ... M3: =DRE_12M!M4 -> 1611.2482
A4: Saídas | B4: =DRE_12M!B5+DRE_12M!B7 -> 18407.4 | C4: =DRE_12M!C5+DRE_12M!C7 -> 18419.622 | D4: =DRE_12M!D5+DRE_12M!D7 -> 18432.211 | E4: =DRE_12M!E5+DRE_12M!E7 -> 18445.177 | F4: =DRE_12M!F5+DRE_12M!F7 -> 18458.532 | G4: =DRE_12M!G5+DRE_12M!G7 -> 18472.288 | H4: =DRE_12M!H5+DRE_12M!H7 -> 18486.457 | I4: =DRE_12M!I5+DRE_12M!I7 -> 18501.051 | ... M4: =DRE_12M!M5+DRE_12M!M7 -> 18563.937
A5: Fluxo Líquido | B5: =B3-B4 -> -17243.4 | C5: =C3-C4 -> -17220.702 | D5: =D3-D4 -> -17197.323 | E5: =E3-E4 -> -17173.243 | F5: =F3-F4 -> -17148.44 | G5: =G3-G4 -> -17122.893 | H5: =H3-H4 -> -17096.58 | I5: =I3-I4 -> -17069.477 | ... M5: =M3-M4 -> -16952.689
A6: Saldo Final | B6: =B2+B5 -> -17243.4 | C6: =C2+C5 -> -34464.102 | D6: =D2+D5 -> -51661.425 | E6: =E2+E5 -> -68834.668 | F6: =F2+F5 -> -85983.108 | G6: =G2+G5 -> -103106 | H6: =H2+H5 -> -120202.58 | I6: =I2+I5 -> -137272.06 | ... M6: =M2+M5 -> -205262.31

Sheet Indicadores
A1: INDICADOR | B1: VALOR | C1: FÓRMULA/INTERPRETAÇÃO
A2: Alunos ativos | B2: =COUNTIF(Alunos!G:G,"Ativo") -> 5 | C2: Base atual
A3: Ticket médio | B3: =IFERROR(SUM(Alunos!F:F)/B2,0) -> 196 | C3: Receita média por aluno
A4: Cancelamentos | B4: =COUNTIF(Alunos!G:G,"Cancelado") -> 1 | C4: Período cadastrado
A5: Churn | B5: =IFERROR(B4/(B2+B4),0) -> 0.16666667 | C5: Cancelamentos / base inicial aproximada
A6: Leads | B6: =COUNTA(Leads!B:B)-1 -> 5 | C6: Total de leads
A7: Novos alunos | B7: =COUNTIF(Leads!G:G,"Sim") -> 3 | C7: Conversões
A8: Conversão de leads | B8: =IFERROR(B7/B6,0) -> 0.6 | C8: Novos alunos / leads
A9: CAC real | B9: =IFERROR(SUM(Leads!I:I)/B7,0) -> 166.66667 | C9: Marketing/comercial por novo aluno
A10: LTV estimado | B10: =IFERROR(B3*Premissas!B7/Premissas!B6,0) -> 392000 | C10: Ticket × margem / churn
A11: Receita mensal atual | B11: =SUM(Receitas!G:G) -> 1060 | C11: Receita recebida
A12: Margem contribuição média | B12: =IFERROR(DRE_12M!B6/DRE_12M!B4,0) -> 0.65 | C12: Margem após variáveis
A13: Ponto de equilíbrio | B13: =IFERROR(Premissas!B10/B12,0) -> 27692.308 | C13: Receita necessária para cobrir custos fixos
A14: Ocupação média das turmas | B14: =AVERAGE(Turmas!I:I) -> 0.71439394 | C14: Capacidade ocupada

Sheet Margem_Modalidades
A1: Modalidade | B1: Alunos | C1: Receita Estimada | D1: Custos Diretos | E1: Margem Contribuição | F1: Margem %
A2: Musculação | B2: =COUNTIF(Alunos!C:C,A2) -> 2 | C2: =SUMIF(Alunos!C:C,A2,Alunos!F:F) -> 300 | D2: =SUMIF(Turmas!B:B,A2,Turmas!J:J) -> 13500 | E2: =C2-D2 -> -13200 | F2: =IFERROR(E2/C2,0) -> -44
A3: Jiu-jítsu | B3: =COUNTIF(Alunos!C:C,A3) -> 1 | C3: =SUMIF(Alunos!C:C,A3,Alunos!F:F) -> 190 | D3: =SUMIF(Turmas!B:B,A3,Turmas!J:J) -> 1440 | E3: =C3-D3 -> -1250 | F3: =IFERROR(E3/C3,0) -> -6.5789474
A4: Muay Thai | B4: =COUNTIF(Alunos!C:C,A4) -> 1 | C4: =SUMIF(Alunos!C:C,A4,Alunos!F:F) -> 220 | D4: =SUMIF(Turmas!B:B,A4,Turmas!J:J) -> 960 | E4: =C4-D4 -> -740 | F4: =IFERROR(E4/C4,0) -> -3.3636364
A5: Capoeira | B5: =COUNTIF(Alunos!C:C,A5) -> 1 | C5: =SUMIF(Alunos!C:C,A5,Alunos!F:F) -> 130 | D5: =SUMIF(Turmas!B:B,A5,Turmas!J:J) -> 400 | E5: =C5-D5 -> -270 | F5: =IFERROR(E5/C5,0) -> -2.0769231
A6: Karatê | B6: =COUNTIF(Alunos!C:C,A6) -> 0 | C6: =SUMIF(Alunos!C:C,A6,Alunos!F:F) -> 0 | D6: =SUMIF(Turmas!B:B,A6,Turmas!J:J) -> 240 | E6: =C6-D6 -> -240 | F6: =IFERROR(E6/C6,0) -> 0
A7: Balé | B7: =COUNTIF(Alunos!C:C,A7) -> 1 | C7: =SUMIF(Alunos!C:C,A7,Alunos!F:F) -> 140 | D7: =SUMIF(Turmas!B:B,A7,Turmas!J:J) -> 240 | E7: =C7-D7 -> -100 | F7: =IFERROR(E7/C7,0) -> -0.71428571

Sheet Ocupacao_Horarios
A1: Horário | B1: Capacidade | C1: Matriculados | D1: Ocupação % | E1: Presença Média | F1: Status
A2: 06-08h | B2: 8 | C2: 7 | D2: =IFERROR(C2/B2,0) -> 0.875 | E2: 6.2 | F2: =IF(D2>=0.8,"Alta",IF(D2>=0.5,"Média","Baixa")) -> Alta
A3: 08-10h | B3: 8 | C3: 6 | D3: =IFERROR(C3/B3,0) -> 0.75 | E3: 5 | F3: =IF(D3>=0.8,"Alta",IF(D3>=0.5,"Média","Baixa")) -> Média
A4: 10-12h | B4: 0 | C4: 0 | D4: =IFERROR(C4/B4,0) -> 0 | E4: 0 | F4: =IF(D4>=0.8,"Alta",IF(D4>=0.5,"Média","Baixa")) -> Baixa
A5: 12-14h | B5: 0 | C5: 0 | D5: =IFERROR(C5/B5,0) -> 0 | E5: 0 | F5: =IF(D5>=0.8,"Alta",IF(D5>=0.5,"Média","Baixa")) -> Baixa
A6: 14-16h | B6: 0 | C6: 0 | D6: =IFERROR(C6/B6,0) -> 0 | E6: 0 | F6: =IF(D6>=0.8,"Alta",IF(D6>=0.5,"Média","Baixa")) -> Baixa
A7: 16-18h | B7: 0 | C7: 0 | D7: =IFERROR(C7/B7,0) -> 0 | E7: 0 | F7: =IF(D7>=0.8,"Alta",IF(D7>=0.5,"Média","Baixa")) -> Baixa
A8: 18-20h | B8: 28 | C8: 26 | D8: =IFERROR(C8/B8,0) -> 0.92857143 | E8: 22 | F8: =IF(D8>=0.8,"Alta",IF(D8>=0.5,"Média","Baixa")) -> Alta
A9: 20-22h | B9: 40 | C9: 33 | D9: =IFERROR(C9/B9,0) -> 0.825 | E9: 27 | F9: =IF(D9>=0.8,"Alta",IF(D9>=0.5,"Média","Baixa")) -> Alta

Sheet Churn_Cancelamentos
A1: Mês | B1: Base Inicial | C1: Novos Alunos | D1: Cancelamentos | E1: Base Final | F1: Churn % | G1: Retenção %
A2: Mês 1 | B2: 100 | C2: 5 | D2: 3 | E2: =B2+C2-D2 -> 102 | F2: =IFERROR(D2/B2,0) -> 0.03 | G2: =1-F2 -> 0.97
A3: Mês 2 | B3: =E2 -> 102 | C3: 5 | D3: 3 | E3: =B3+C3-D3 -> 104 | F3: =IFERROR(D3/B3,0) -> 0.029411765 | G3: =1-F3 -> 0.97058824
A4: Mês 3 | B4: =E3 -> 104 | C4: 5 | D4: 3 | E4: =B4+C4-D4 -> 106 | F4: =IFERROR(D4/B4,0) -> 0.028846154 | G4: =1-F4 -> 0.97115385
A5: Mês 4 | B5: =E4 -> 106 | C5: 5 | D5: 3 | E5: =B5+C5-D5 -> 108 | F5: =IFERROR(D5/B5,0) -> 0.028301887 | G5: =1-F5 -> 0.97169811
A6: Mês 5 | B6: =E5 -> 108 | C6: 5 | D6: 3 | E6: =B6+C6-D6 -> 110 | F6: =IFERROR(D6/B6,0) -> 0.027777778 | G6: =1-F6 -> 0.97222222
A7: Mês 6 | B7: =E6 -> 110 | C7: 5 | D7: 3 | E7: =B7+C7-D7 -> 112 | F7: =IFERROR(D7/B7,0) -> 0.027272727 | G7: =1-F7 -> 0.97272727
A8: Mês 7 | B8: =E7 -> 112 | C8: 5 | D8: 3 | E8: =B8+C8-D8 -> 114 | F8: =IFERROR(D8/B8,0) -> 0.026785714 | G8: =1-F8 -> 0.97321429
A9: Mês 8 | B9: =E8 -> 114 | C9: 5 | D9: 3 | E9: =B9+C9-D9 -> 116 | F9: =IFERROR(D9/B9,0) -> 0.026315789 | G9: =1-F9 -> 0.97368421
A10: Mês 9 | B10: =E9 -> 116 | C10: 5 | D10: 3 | E10: =B10+C10-D10 -> 118 | F10: =IFERROR(D10/B10,0) -> 0.025862069 | G10: =1-F10 -> 0.97413793
A11: Mês 10 | B11: =E10 -> 118 | C11: 5 | D11: 3 | E11: =B11+C11-D11 -> 120 | F11: =IFERROR(D11/B11,0) -> 0.025423729 | G11: =1-F11 -> 0.97457627
A12: Mês 11 | B12: =E11 -> 120 | C12: 5 | D12: 3 | E12: =B12+C12-D12 -> 122 | F12: =IFERROR(D12/B12,0) -> 0.025 | G12: =1-F12 -> 0.975
A13: Mês 12 | B13: =E12 -> 122 | C13: 5 | D13: 3 | E13: =B13+C13-D13 -> 124 | F13: =IFERROR(D13/B13,0) -> 0.024590164 | G13: =1-F13 -> 0.97540984

Sheet Projecao_Faturamento
A1: Mês | B1: Alunos Projetados | C1: Ticket Médio | D1: Faturamento Projetado | E1: Faturamento Acumulado
A2: Mês 1 | B2: =Indicadores!B2 -> 5 | C2: =Indicadores!B3 -> 196 | D2: =B2*C2 -> 980 | E2: =D2 -> 980
A3: Mês 2 | B3: =B2*(1+Premissas!$B$9) -> 5.15 | C3: =Indicadores!B3 -> 196 | D3: =B3*C3 -> 1009.4 | E3: =E2+D3 -> 1989.4
A4: Mês 3 | B4: =B3*(1+Premissas!$B$9) -> 5.3045 | C4: =Indicadores!B3 -> 196 | D4: =B4*C4 -> 1039.682 | E4: =E3+D4 -> 3029.082
A5: Mês 4 | B5: =B4*(1+Premissas!$B$9) -> 5.463635 | C5: =Indicadores!B3 -> 196 | D5: =B5*C5 -> 1070.8725 | E5: =E4+D5 -> 4099.9545
A6: Mês 5 | B6: =B5*(1+Premissas!$B$9) -> 5.6275441 | C6: =Indicadores!B3 -> 196 | D6: =B6*C6 -> 1102.9986 | E6: =E5+D6 -> 5202.9531
A7: Mês 6 | B7: =B6*(1+Premissas!$B$9) -> 5.7963704 | C7: =Indicadores!B3 -> 196 | D7: =B7*C7 -> 1136.0886 | E7: =E6+D7 -> 6339.0417
A8: Mês 7 | B8: =B7*(1+Premissas!$B$9) -> 5.9702615 | C8: =Indicadores!B3 -> 196 | D8: =B8*C8 -> 1170.1713 | E8: =E7+D8 -> 7509.2129
A9: Mês 8 | B9: =B8*(1+Premissas!$B$9) -> 6.1493693 | C9: =Indicadores!B3 -> 196 | D9: =B9*C9 -> 1205.2764 | E9: =E8+D9 -> 8714.4893
A10: Mês 9 | B10: =B9*(1+Premissas!$B$9) -> 6.3338504 | C10: =Indicadores!B3 -> 196 | D10: =B10*C10 -> 1241.4347 | E10: =E9+D10 -> 9955.924
A11: Mês 10 | B11: =B10*(1+Premissas!$B$9) -> 6.5238659 | C11: =Indicadores!B3 -> 196 | D11: =B11*C11 -> 1278.6777 | E11: =E10+D11 -> 11234.602
A12: Mês 11 | B12: =B11*(1+Premissas!$B$9) -> 6.7195819 | C12: =Indicadores!B3 -> 196 | D12: =B12*C12 -> 1317.0381 | E12: =E11+D12 -> 12551.64
A13: Mês 12 | B13: =B12*(1+Premissas!$B$9) -> 6.9211694 | C13: =Indicadores!B3 -> 196 | D13: =B13*C13 -> 1356.5492 | E13: =E12+D13 -> 13908.189

Sheet Dashboard_Executivo
A1: DASHBOARD EXECUTIVO – ACADEMIA
A3: ALUNOS ATIVOS | C3: RECEITA ATUAL | E3: TICKET MÉDIO | G3: CHURN | I3: CAC | K3: LTV ESTIMADO
A4: =Indicadores!B2 -> 5 | C4: =Indicadores!B11 -> 1060 | E4: =Indicadores!B3 -> 196 | G4: =Indicadores!B5 -> 0.16666667 | I4: =Indicadores!B9 -> 166.66667 | K4: =Indicadores!B10 -> 392000
A6: MARGEM CONTRIB. | C6: PONTO DE EQUILÍBRIO | E6: OCUPAÇÃO MÉDIA | G6: NOVOS ALUNOS | I6: CONVERSÃO | K6: CANCELAMENTOS
A7: =Indicadores!B12 -> 0.65 | C7: =Indicadores!B13 -> 27692.308 | E7: =Indicadores!B14 -> 0.71439394 | G7: =Indicadores!B7 -> 3 | I7: =Indicadores!B8 -> 0.6 | K7: =Indicadores!B4 -> 1
A10: DRE – Resultado Operacional
